Qt/QtCore.py
Qt/QtGui.py
Qt/QtMultimedia.py
Qt/QtNetwork.py
Qt/QtWebEngineCore.py
Qt/QtWebEngineWidgets.py
Qt/QtWidgets.py
Qt/__init__.py
Qt/promote_enums.py
qtshim-1.2.dist-info/METADATA
qtshim-1.2.dist-info/WHEEL
qtshim-1.2.dist-info/top_level.txt
qtshim-1.2.dist-info/RECORD
